powerpwn/__init__.py
powerpwn/main.py
powerpwn/cli/__init__.py
powerpwn/cli/arguments.py
powerpwn/cli/const.py
powerpwn/cli/runners.py
powerpwn/common/__init__.py
powerpwn/common/cache/__init__.py
powerpwn/common/cache/cached_entity.py
powerpwn/common/cache/string_key_value_cache.py
powerpwn/common/cache/token_cache.py
powerpwn/common/file_browser/__init__.py
powerpwn/common/file_browser/app.py
powerpwn/common/file_browser/templates/__init__.py
powerpwn/common/file_browser/templates/file_view_template.py
powerpwn/common/file_browser/templates/html_template.py
powerpwn/common/file_browser/templates/no_data.py
powerpwn/copilot/__init__.py
powerpwn/copilot/consts.py
powerpwn/copilot/main.py
powerpwn/copilot/chat_automator/__init__.py
powerpwn/copilot/chat_automator/chat_automator.py
powerpwn/copilot/chat_automator/log_formatting/__init__.py
powerpwn/copilot/chat_automator/log_formatting/automated_chat_log_formatter.py
powerpwn/copilot/chat_automator/log_formatting/automated_chat_websocket_message_formatter.py
powerpwn/copilot/chat_automator/log_formatting/log_type_enum.py
powerpwn/copilot/copilot_connector/__init__.py
powerpwn/copilot/copilot_connector/copilot_connector.py
powerpwn/copilot/dump/__init__.py
powerpwn/copilot/dump/dump.py
powerpwn/copilot/dump/input_extractor/__init__.py
powerpwn/copilot/dump/input_extractor/document_input_extractor.py
powerpwn/copilot/dump/input_extractor/input_file_reader.py
powerpwn/copilot/enums/__init__.py
powerpwn/copilot/enums/copilot_scenario_enum.py
powerpwn/copilot/enums/message_type_enum.py
powerpwn/copilot/enums/verbose_enum.py
powerpwn/copilot/exceptions/__init__.py
powerpwn/copilot/exceptions/copilot_connected_user_mismatch.py
powerpwn/copilot/exceptions/copilot_connection_failed_exception.py
powerpwn/copilot/exceptions/copilot_connection_not_initialized_exception.py
powerpwn/copilot/gui/__init__.py
powerpwn/copilot/gui/gui.py
powerpwn/copilot/interactive_chat/__init__.py
powerpwn-5.0.0.dist-info/METADATA
powerpwn-5.0.0.dist-info/WHEEL
powerpwn-5.0.0.dist-info/entry_points.txt
powerpwn-5.0.0.dist-info/top_level.txt
powerpwn-5.0.0.dist-info/RECORD
