Metadata-Version: 2.4
Name: powerpwn
Version: 5.0.0
Author: Michael Bargury, Lana Salameh and Avishai Efrat
Requires-Dist: pydantic[email]==1.10.7
Requires-Dist: pydantic==1.10.7
Requires-Dist: swagger-ui-py==22.7.13
Requires-Dist: Flask==2.2.5
Requires-Dist: requests>=2.31.0
Requires-Dist: msal>=1.20.0
Requires-Dist: responses>=0.23.1
Requires-Dist: pytest>=8.1.1
Requires-Dist: prance>=23.6.21.0
Requires-Dist: openapi>=1.1.0
Requires-Dist: openapi-spec-validator>=0.5.6
Requires-Dist: jsf>=0.7.1
Requires-Dist: pillow>=10.3.0
Requires-Dist: scandir>=1.10.0
Requires-Dist: backports.shutil-get-terminal-size>=1.0.0
Requires-Dist: art>=6.1
Requires-Dist: typing_extensions<4.6.0
Requires-Dist: pyjwt>=2.6.0
Requires-Dist: websockets>=12.0.0
Requires-Dist: pandas
Requires-Dist: xlsxwriter>=3.2.0
Requires-Dist: xmltodict
